LICENSE.TXT
README.md
setup.py
rocket_2/__init__.py
rocket_2/rocket_2.py
rocket_2.egg-info/PKG-INFO
rocket_2.egg-info/SOURCES.txt
rocket_2.egg-info/dependency_links.txt
rocket_2.egg-info/top_level.txt