Metadata-Version: 2.1
Name: rocket_2
Version: 1.0.0
Summary: An awesome package that does something
Home-page: http://pypi.python.org/pypi/rocket/
Author: Wassim
Author-email: w.rahmoun@esi-sba.dz
License: LICENSE.txt
License-File: LICENSE.TXT
